thesisbot/__init__.py
thesisbot/decision_engine.py
thesisbot-0.1.dist-info/METADATA
thesisbot-0.1.dist-info/WHEEL
thesisbot-0.1.dist-info/top_level.txt
thesisbot-0.1.dist-info/RECORD
