Metadata-Version: 2.1
Name: thesisbot
Version: 0.1
Summary: A library for decision making using expert systems and text similarity
Home-page: https://github.com/yourusername/mylibrary
Author: Your Name
Author-email: your.email@example.com
Classifier: Programming Language :: Python :: 3
Classifier: License :: OSI Approved :: MIT License
Classifier: Operating System :: OS Independent
Requires-Python: >=3.6
Requires-Dist: experta
Requires-Dist: scikit-learn
Requires-Dist: flask
